MANIFEST.in
README.rst
bootstrap.py
buildout.cfg
ez_setup.py
requirements.txt
setup.py
docs/changes.rst
scripts/vboxn
scripts/vboxn-init
scripts/vboxn-postinstall
scripts/vboxn-scancodes
share/archlinux/latest/aif-dieter-t420s.cfg
share/archlinux/latest/aif-generic.cfg
share/archlinux/latest/postinstall/base.sh
share/archlinux/latest/postinstall/netcfg.sh
share/archlinux/latest/postinstall/vagrant.sh
share/ubuntu/12.04/preseed.cfg
share/ubuntu/12.04/postinstall/base.sh
share/ubuntu/12.04/postinstall/etc.sh
share/ubuntu/12.04/postinstall/finally.sh
share/ubuntu/12.04/postinstall/libmemcached.sh
share/ubuntu/12.04/postinstall/nginx.sh
share/ubuntu/12.04/postinstall/python2-libs.sh
share/ubuntu/12.04/postinstall/rabbitmq.sh
share/ubuntu/12.04/postinstall/vagrant.sh
share/ubuntu/12.04/postinstall/vboxn.log
vboxn/__init__.py
vboxn/client.py
vboxn/commands.py
vboxn/errors.py
vboxn/ui.py
vboxn/utils.py
vboxn.egg-info/PKG-INFO
vboxn.egg-info/SOURCES.txt
vboxn.egg-info/dependency_links.txt
vboxn.egg-info/requires.txt
vboxn.egg-info/top_level.txt