Metadata-Version: 1.1
Name: vboxn
Version: 0.2.2
Summary: Automate the creation and provisioning of VirtualBox machines.
Home-page: https://github.com/devopsni/vboxn
Author: Gerard Flanagan
Author-email: gflanagan@devopsni.com
License: BSD
Download-URL: http://pypi.python.org/packages/source/v/vboxn/vboxn-0.2.2.tar.gz
Platform: UNKNOWN
Classifier: Programming Language :: Python
Classifier: Programming Language :: Other
Classifier: Environment :: Console
Classifier: Operating System :: POSIX
